PyPapertrail/Archive.py
PyPapertrail/Archives.py
PyPapertrail/Destination.py
PyPapertrail/Destinations.py
PyPapertrail/Event.py
PyPapertrail/Exceptions.py
PyPapertrail/Group.py
PyPapertrail/Groups.py
PyPapertrail/Papertrail.py
PyPapertrail/RateLimits.py
PyPapertrail/Results.py
PyPapertrail/SavedSearch.py
PyPapertrail/SavedSearches.py
PyPapertrail/System.py
PyPapertrail/Systems.py
PyPapertrail/Usage.py
PyPapertrail/User.py
PyPapertrail/Users.py
PyPapertrail/apiKey.py
PyPapertrail/common.py
PyPapertrail-1.7.dist-info/LICENSE
PyPapertrail-1.7.dist-info/METADATA
PyPapertrail-1.7.dist-info/WHEEL
PyPapertrail-1.7.dist-info/top_level.txt
PyPapertrail-1.7.dist-info/RECORD
