Metadata-Version: 2.1
Name: PyPapertrail
Version: 1.7
Summary: A python3 API to the Papertrail http api.
Author-email: Peter Nearing <me@peternearing.ca>
Project-URL: Homepage, https://peternearing.ca/pypapertrail
Project-URL: Bug Tracker, https://github.com/pnearing/PyPapertrail/issues
Classifier: Programming Language :: Python :: 3
Classifier: Operating System :: OS Independent
Requires-Python: >=3.10
License-File: LICENSE
